{
    "GUROBI_sb": {
        "time": 300,
        "optimal": false,
        "obj": 1074,
        "sol": [
            [
                129,
                138,
                96,
                59,
                57,
                64,
                99,
                134,
                143,
                2
            ],
            [
                142,
                132,
                118,
                116,
                32,
                48,
                68,
                54,
                37,
                113
            ],
            [
                17,
                50,
                55,
                13,
                69
            ],
            [
                36,
                131,
                58,
                14,
                71
            ],
            [
                63,
                29,
                90,
                84,
                93
            ],
            [
                33,
                88,
                91,
                62,
                18
            ],
            [
                126,
                120,
                122,
                12,
                73
            ],
            [
                31,
                83,
                123,
                137,
                46
            ],
            [
                44,
                52,
                127,
                21,
                16,
                135
            ],
            [
                7,
                47,
                39,
                92,
                74,
                22,
                82
            ],
            [
                4,
                89,
                136,
                41,
                124,
                10,
                67,
                125
            ],
            [
                78,
                72,
                140,
                77,
                86,
                75,
                139,
                109
            ],
            [
                106,
                85,
                80,
                81,
                103
            ],
            [
                11,
                34,
                61,
                98,
                23,
                19,
                97,
                20
            ],
            [
                25,
                43,
                40,
                79,
                28
            ],
            [
                1,
                60,
                65,
                5,
                102,
                108,
                26,
                105,
                114
            ],
            [
                53,
                110,
                107,
                112,
                30,
                115,
                8,
                111
            ],
            [
                3,
                119,
                70,
                94,
                117,
                35,
                128,
                121,
                76
            ],
            [
                104,
                66,
                100,
                133,
                15,
                56,
                130,
                95,
                141,
                6
            ],
            [
                101,
                9,
                45,
                24,
                27,
                38,
                42,
                49,
                87,
                51
            ]
        ]
    }
}